osc_sdk_python/VERSION
osc_sdk_python/__init__.py
osc_sdk_python/authentication.py
osc_sdk_python/call.py
osc_sdk_python/credentials.py
osc_sdk_python/outscale_gateway.py
osc_sdk_python/requester.py
osc_sdk_python/osc-api/outscale.yaml
osc_sdk_python/resources/gateway_errors.yaml
osc_sdk_python-0.37.0.dist-info/licenses/LICENSE
osc_sdk_python-0.37.0.dist-info/METADATA
osc_sdk_python-0.37.0.dist-info/WHEEL
osc_sdk_python-0.37.0.dist-info/top_level.txt
osc_sdk_python-0.37.0.dist-info/RECORD
