Metadata-Version: 2.4
Name: osc_sdk_python
Version: 0.37.0
Summary: Outscale Gateway python SDK
Home-page: https://github.com/outscale/osc_sdk_python
Author: Outscal SAS
Author-email: opensource@outscale.com
Classifier: Programming Language :: Python :: 3
Classifier: License :: OSI Approved :: BSD License
Classifier: Operating System :: OS Independent
License-File: LICENSE
Requires-Dist: requests>=2.20.0
Requires-Dist: ruamel.yaml==0.18.15
Dynamic: author
Dynamic: author-email
Dynamic: classifier
Dynamic: description
Dynamic: description-content-type
Dynamic: home-page
Dynamic: license-file
Dynamic: requires-dist
Dynamic: summary
